ansys/pre_commit_hooks/VERSION
ansys/pre_commit_hooks/__init__.py
ansys/pre_commit_hooks/add_license_headers.py
ansys/pre_commit_hooks/tech_review.py
ansys/pre_commit_hooks/__pycache__/__init__.cpython-312.pyc
ansys/pre_commit_hooks/__pycache__/tech_review.cpython-312.pyc
ansys/pre_commit_hooks/assets/licenses.json
ansys/pre_commit_hooks/assets/.reuse/templates/ansys.jinja2
ansys/pre_commit_hooks/assets/LICENSES/MIT.txt
ansys/pre_commit_hooks/templates/AUTHORS
ansys/pre_commit_hooks/templates/CODE_OF_CONDUCT.md
ansys/pre_commit_hooks/templates/CONTRIBUTING.md
ansys/pre_commit_hooks/templates/CONTRIBUTORS.md
ansys/pre_commit_hooks/templates/LICENSE
ansys/pre_commit_hooks/templates/README.md
ansys/pre_commit_hooks/templates/README.rst
ansys/pre_commit_hooks/templates/dependabot.yml
ansys_pre_commit_hooks-0.5.2.dist-info/AUTHORS
ansys_pre_commit_hooks-0.5.2.dist-info/LICENSE
ansys_pre_commit_hooks-0.5.2.dist-info/METADATA
ansys_pre_commit_hooks-0.5.2.dist-info/WHEEL
ansys_pre_commit_hooks-0.5.2.dist-info/entry_points.txt
ansys_pre_commit_hooks-0.5.2.dist-info/top_level.txt
ansys_pre_commit_hooks-0.5.2.dist-info/RECORD
