Metadata-Version: 2.2
Name: ansys-pre-commit-hooks
Version: 0.5.2
Summary: A Python wrapper to create Ansys-tailored pre-commit hooks
Home-page: https://github.com/ansys/pre-commit-hooks
Author: ANSYS, Inc.
Author-email: pyansys.core@ansys.com
Maintainer: ANSYS, Inc.
Maintainer-email: pyansys.core@ansys.com
License: MIT
Project-URL: Source, https://github.com/ansys/pre-commit-hooks/
Project-URL: Tracker, https://github.com/ansys/pre-commit-hooks/issues
Project-URL: Homepage, https://github.com/ansys/pre-commit-hooks
Project-URL: Documentation, https://pre-commit-hooks.docs.pyansys.com
Classifier: Development Status :: 4 - Beta
Classifier: Intended Audience :: Science/Research
Classifier: Topic :: Scientific/Engineering :: Information Analysis
Classifier: License :: OSI Approved :: MIT License
Classifier: Operating System :: OS Independent
Classifier: Programming Language :: Python :: 3.9
Classifier: Programming Language :: Python :: 3.10
Classifier: Programming Language :: Python :: 3.11
Classifier: Programming Language :: Python :: 3.12
Requires-Python: >=3.9,<4
License-File: LICENSE
License-File: AUTHORS
Requires-Dist: GitPython==3.1.44
Requires-Dist: importlib-metadata==8.6.1
Requires-Dist: Jinja2==3.1.5
Requires-Dist: reuse==5.0.2
Requires-Dist: requests==2.32.3
Requires-Dist: semver==3.0.4
Requires-Dist: toml==0.10.2
Provides-Extra: doc
Requires-Dist: ansys-sphinx-theme[autoapi]==1.3.2; extra == "doc"
Requires-Dist: numpydoc==1.8.0; extra == "doc"
Requires-Dist: sphinx==8.2.1; extra == "doc"
Requires-Dist: sphinx-autodoc-typehints==3.1.0; extra == "doc"
Requires-Dist: sphinx-copybutton==0.5.1; extra == "doc"
Requires-Dist: sphinx_design==0.6.1; extra == "doc"
Provides-Extra: tests
Requires-Dist: pytest==8.3.4; extra == "tests"
Requires-Dist: pytest-cov==6.0.0; extra == "tests"
Dynamic: author
Dynamic: author-email
Dynamic: classifier
Dynamic: description
Dynamic: home-page
Dynamic: license
Dynamic: maintainer
Dynamic: maintainer-email
Dynamic: project-url
Dynamic: provides-extra
Dynamic: requires-dist
Dynamic: requires-python
Dynamic: summary
